yabencode/__init__.py
yabencode/command_line.py
yabencode-0.2.1.dist-info/LICENSE.txt
yabencode-0.2.1.dist-info/METADATA
yabencode-0.2.1.dist-info/WHEEL
yabencode-0.2.1.dist-info/entry_points.txt
yabencode-0.2.1.dist-info/top_level.txt
yabencode-0.2.1.dist-info/RECORD
