Metadata-Version: 2.1
Name: yabencode
Version: 0.2.1
Summary: YABEncode - Yet Another Bencode module
Home-page: https://github.com/TheAMM/YABEncode
Author: AMM
Author-email: the.actual.amm@gmail.com
License: MIT
Keywords: bencode bdecode torrent bencoding
Classifier: Development Status :: 4 - Beta
Classifier: Intended Audience :: Developers
Classifier: License :: OSI Approved :: MIT License
Classifier: Programming Language :: Python :: 3 :: Only
Classifier: Programming Language :: Python :: 3
Classifier: Programming Language :: Python :: 3.3
Classifier: Programming Language :: Python :: 3.4
Classifier: Programming Language :: Python :: 3.5
Classifier: Programming Language :: Python :: 3.6
Classifier: Programming Language :: Python :: 3.7
Classifier: Programming Language :: Python :: 3.8
Classifier: Programming Language :: Python :: 3.9
Classifier: Programming Language :: Python :: 3.10
Requires-Python: >=3.3, <4
License-File: LICENSE.txt
